touchpoint/__init__.py
touchpoint/employee.py
touchpoint/item.py
touchpoint/location.py
touchpoint/touchpoint.py
touchpoint-0.0.1.dist-info/LICENSE.md
touchpoint-0.0.1.dist-info/METADATA
touchpoint-0.0.1.dist-info/WHEEL
touchpoint-0.0.1.dist-info/top_level.txt
touchpoint-0.0.1.dist-info/RECORD
