Metadata-Version: 2.1
Name: touchpoint
Version: 0.0.1
Summary: Touchpoint External API
Home-page: https://github.com/zappospizza/touchpoint-python
Author: banthaherder
Author-email: devops@zappospizza.com
License: MIT License
